[
    {
        "16.02.2024": {
            "EUR": {
                "sale": 40.7718,
                "purchase": 40.7718
            },
            "USD": {
                "sale": 37.9484,
                "purchase": 37.9484
            }
        }
    },
    {
        "15.02.2024": {
            "EUR": {
                "sale": 40.8684,
                "purchase": 40.8684
            },
            "USD": {
                "sale": 38.1734,
                "purchase": 38.1734
            }
        }
    }
]